{"Isumi Sakuraba": "https://cdn.myanimelist.net/images/characters/11/449885.jpg", "Spike Spiegel": "https://cdn.myanimelist.net/images/characters/4/50197.jpg", "Faye Valentine": "https://cdn.myanimelist.net/images/characters/15/264961.jpg", "Jet Black": "https://cdn.myanimelist.net/images/characters/11/253723.jpg", "Ein ": "https://cdn.myanimelist.net/images/characters/5/30624.jpg", "Ichigo Kurosaki": "https://cdn.myanimelist.net/images/characters/3/89190.jpg", "Rukia Kuchiki": "https://cdn.myanimelist.net/images/characters/2/78215.jpg", "Orihime Inoue": "https://cdn.myanimelist.net/images/characters/12/97695.jpg", "Edward Elric": "https://cdn.myanimelist.net/images/characters/9/72533.jpg", "Alphonse Elric": "https://cdn.myanimelist.net/images/characters/5/54265.jpg", "Sasuke Uchiha": "https://cdn.myanimelist.net/images/characters/9/131317.jpg", "Itachi Uchiha": "https://cdn.myanimelist.net/images/characters/9/284122.jpg", "Ippo Makunouchi": "https://cdn.myanimelist.net/images/characters/11/32678.jpg", "Edward Wong Hau Pepelu Tivrusky IV": "https://cdn.myanimelist.net/images/characters/16/30533.jpg", "Naruto Uzumaki": "https://cdn.myanimelist.net/images/characters/2/284121.jpg", "Haruhi Fujioka": "https://cdn.myanimelist.net/images/characters/13/55779.jpg", "Tamaki Suou": "https://cdn.myanimelist.net/images/characters/3/48467.jpg", "Mitsukuni Haninozuka": "https://cdn.myanimelist.net/images/characters/13/48471.jpg", "Takashi Morinozuka": "https://cdn.myanimelist.net/images/characters/11/128685.jpg", "Hikaru Hitachiin": "https://cdn.myanimelist.net/images/characters/2/48468.jpg", "Kyouya Ootori": "https://cdn.myanimelist.net/images/characters/13/90675.jpg", "Kaoru Hitachiin": "https://cdn.myanimelist.net/images/characters/9/48469.jpg", "Renge Houshakuji": "https://cdn.myanimelist.net/images/characters/10/55457.jpg", "Ging Freecss": "https://cdn.myanimelist.net/images/characters/2/231795.jpg", "Killua Zoldyck": "https://cdn.myanimelist.net/images/characters/2/327920.jpg", "Kurapika ": "https://cdn.myanimelist.net/images/characters/4/174563.jpg", "Leorio Paladiknight": "https://cdn.myanimelist.net/images/characters/11/174519.jpg", "Gon Freecss": "https://cdn.myanimelist.net/images/characters/11/174517.jpg", "Hisoka Morow": "https://cdn.myanimelist.net/images/characters/3/174561.jpg", "Ovan ": "https://cdn.myanimelist.net/images/characters/13/61258.jpg", "Haseo ": "https://cdn.myanimelist.net/images/characters/12/86036.jpg", "Shino ": "https://cdn.myanimelist.net/images/characters/8/85961.jpg", "Tabby ": "https://cdn.myanimelist.net/images/characters/10/85962.jpg", "Phyllo ": "https://cdn.myanimelist.net/images/characters/11/137791.jpg", "Sakisaka ": "https://cdn.myanimelist.net/images/characters/10/131571.jpg", "Tawaraya ": "https://cdn.myanimelist.net/images/characters/7/4383.jpg", "Tsukasa ": "https://cdn.myanimelist.net/images/characters/2/86095.jpg", "Luffy Monkey D.": "https://cdn.myanimelist.net/images/characters/9/310307.jpg", "Subaru ": "https://cdn.myanimelist.net/images/characters/14/85930.jpg", "Train Heartnet": "https://cdn.myanimelist.net/images/characters/15/78799.jpg", "Sven Vollfied": "https://cdn.myanimelist.net/images/characters/5/58282.jpg", "Eve ": "https://cdn.myanimelist.net/images/characters/12/52806.jpg", "Rinslet Walker": "https://cdn.myanimelist.net/images/characters/16/78923.jpg", "Ban Midou": "https://cdn.myanimelist.net/images/characters/8/30608.jpg", "Ginji Amano": "https://cdn.myanimelist.net/images/characters/16/30607.jpg", "Kazuki Fuuchouin": "https://cdn.myanimelist.net/images/characters/12/33496.jpg", "Shido Fuyuki": "https://cdn.myanimelist.net/images/characters/2/30668.jpg", "Hevn ": "https://cdn.myanimelist.net/images/characters/16/30579.jpg", "Natsumi Mizuki": "https://cdn.myanimelist.net/images/characters/11/30587.jpg", "Kuroudo Akabane": "https://cdn.myanimelist.net/images/characters/11/30582.jpg", "Himiko Kudou": "https://cdn.myanimelist.net/images/characters/12/30585.jpg", "Paul Wang": "https://cdn.myanimelist.net/images/characters/5/30588.jpg", "MakubeX ": "https://cdn.myanimelist.net/images/characters/16/30729.jpg", "Juubei Kakei": "https://cdn.myanimelist.net/images/characters/10/66595.jpg", "Illumi Zoldyck": "https://cdn.myanimelist.net/images/characters/8/174521.jpg", "Chrollo Lucilfer": "https://cdn.myanimelist.net/images/characters/4/182387.jpg", "Zeno Zoldyck": "https://cdn.myanimelist.net/images/characters/5/193007.jpg", "Silva Zoldyck": "https://cdn.myanimelist.net/images/characters/4/198609.jpg", "Robin Nico": "https://cdn.myanimelist.net/images/characters/13/136773.jpg", "Zoro Roronoa": "https://cdn.myanimelist.net/images/characters/3/100534.jpg", "Winry Rockbell": "https://cdn.myanimelist.net/images/characters/15/84336.jpg", "Franky ": "https://cdn.myanimelist.net/images/characters/13/210053.jpg", "Pinako Rockbell": "https://cdn.myanimelist.net/images/characters/6/81200.jpg", "Scar ": "https://cdn.myanimelist.net/images/characters/3/31591.jpg", "Izumi Curtis": "https://cdn.myanimelist.net/images/characters/5/85257.jpg", "Roy Mustang": "https://cdn.myanimelist.net/images/characters/7/72983.jpg", "Maes Hughes": "https://cdn.myanimelist.net/images/characters/13/73469.jpg", "Riza Hawkeye": "https://cdn.myanimelist.net/images/characters/3/451785.jpg", "L Lawliet": "https://cdn.myanimelist.net/images/characters/10/249647.jpg", "Kazuma Azuma": "https://cdn.myanimelist.net/images/characters/5/33059.jpg", "Kyousuke Kawachi": "https://cdn.myanimelist.net/images/characters/3/33047.jpg", "Tsukino Azusagawa": "https://cdn.myanimelist.net/images/characters/6/33056.jpg", "Ryuk ": "https://cdn.myanimelist.net/images/characters/10/59125.jpg", "Kai Suwabara": "https://cdn.myanimelist.net/images/characters/11/33042.jpg", "Shigeru Kanmuri": "https://cdn.myanimelist.net/images/characters/11/33045.jpg", "Ken Matsushiro": "https://cdn.myanimelist.net/images/characters/2/33044.jpg", "Ryo Kuroyanagi": "https://cdn.myanimelist.net/images/characters/9/33052.jpg", "Light Yagami": "https://cdn.myanimelist.net/images/characters/6/63870.jpg", "Pierrot Bolneze": "https://cdn.myanimelist.net/images/characters/11/33049.jpg", "Yuuichi Kirisaki": "https://cdn.myanimelist.net/images/characters/9/111035.jpg", "Yukino Azusagawa": "https://cdn.myanimelist.net/images/characters/8/110969.jpg", "Kageto Kinoshita": "https://cdn.myanimelist.net/images/characters/7/111036.jpg", "Kakashi Hatake": "https://cdn.myanimelist.net/images/characters/7/284129.jpg", "Rei Ayanami": "https://cdn.myanimelist.net/images/characters/11/314932.jpg", "Kino ": "https://cdn.myanimelist.net/images/characters/4/336511.jpg", "Hermes ": "https://cdn.myanimelist.net/images/characters/5/336494.jpg", "Shinji Ikari": "https://cdn.myanimelist.net/images/characters/5/225177.jpg", "Hikaru Shindou": "https://cdn.myanimelist.net/images/characters/3/173907.jpg", "Sai Fujiwara no": "https://cdn.myanimelist.net/images/characters/2/44575.jpg", "Akari Fujisaki": "https://cdn.myanimelist.net/images/characters/15/28057.jpg", "Akira Touya": "https://cdn.myanimelist.net/images/characters/3/28051.jpg", "Asuka Langley Souryuu": "https://cdn.myanimelist.net/images/characters/12/79465.jpg", "Yuki Mitani": "https://cdn.myanimelist.net/images/characters/13/75070.jpg", "Tetsuo Kaga": "https://cdn.myanimelist.net/images/characters/13/75072.jpg", "Kimihiro Tsutsui": "https://cdn.myanimelist.net/images/characters/2/75251.jpg", "Yoshitaka Waya": "https://cdn.myanimelist.net/images/characters/6/75068.jpg", "Heero Yuy": "https://cdn.myanimelist.net/images/characters/11/40369.jpg", "Shinichiro Isumi": "https://cdn.myanimelist.net/images/characters/3/75095.jpg", "Kousuke Ochi": "https://cdn.myanimelist.net/images/characters/3/337808.jpg", "Seiji Ogata": "https://cdn.myanimelist.net/images/characters/9/75076.jpg", "Duo Maxwell": "https://cdn.myanimelist.net/images/characters/13/40366.jpg", "Shigeo Morishita": "https://cdn.myanimelist.net/images/characters/4/70910.jpg", "Trowa Barton": "https://cdn.myanimelist.net/images/characters/15/40382.jpg", "Kippei Katakura": "https://cdn.myanimelist.net/images/characters/7/30965.jpg", "Yuzuyu Sakashita": "https://cdn.myanimelist.net/images/characters/2/30964.jpg", "Quatre Raberba Winner": "https://cdn.myanimelist.net/images/characters/5/40372.jpg", "Kokoro Tokunaga": "https://cdn.myanimelist.net/images/characters/6/120294.jpg", "Wufei Chang": "https://cdn.myanimelist.net/images/characters/10/277945.jpg", "Reiko Katakura": "https://cdn.myanimelist.net/images/characters/2/134101.jpg", "Satsuki Katakura": "https://cdn.myanimelist.net/images/characters/14/53237.jpg", "Kira Yamato": "https://cdn.myanimelist.net/images/characters/10/72646.jpg", "Athrun Zala": "https://cdn.myanimelist.net/images/characters/6/92453.jpg", "Cagalli Yula Athha": "https://cdn.myanimelist.net/images/characters/16/108057.jpg", "Lacus Clyne": "https://cdn.myanimelist.net/images/characters/12/122415.jpg", "Shinn Asuka": "https://cdn.myanimelist.net/images/characters/13/72918.jpg", "Rey Za Burrel": "https://cdn.myanimelist.net/images/characters/15/30441.jpg", "Stella Loussier": "https://cdn.myanimelist.net/images/characters/10/110217.jpg", "Lunamaria Hawke": "https://cdn.myanimelist.net/images/characters/8/298721.jpg", "Meyrin Hawke": "https://cdn.myanimelist.net/images/characters/9/298730.jpg", "Andrew Waltfeld": "https://cdn.myanimelist.net/images/characters/7/30427.jpg", "Dearka Elsman": "https://cdn.myanimelist.net/images/characters/15/30517.jpg", "Flay Allster": "https://cdn.myanimelist.net/images/characters/11/298709.jpg", "Murrue Ramius": "https://cdn.myanimelist.net/images/characters/10/30432.jpg", "Syaoran ": "https://cdn.myanimelist.net/images/characters/11/88326.jpg", "Sakura ": "https://cdn.myanimelist.net/images/characters/14/47457.jpg", "Fai ": "https://cdn.myanimelist.net/images/characters/9/54499.jpg", "Kurogane ": "https://cdn.myanimelist.net/images/characters/12/77672.jpg", "Kotarou Higuchi": "https://cdn.myanimelist.net/images/characters/2/35117.jpg", "Misha ": "https://cdn.myanimelist.net/images/characters/7/35116.jpg", "Shia ": "https://cdn.myanimelist.net/images/characters/12/109119.jpg", "Takashi Ayanokouji": "https://cdn.myanimelist.net/images/characters/16/109121.jpg", "Koboshi Uematsu": "https://cdn.myanimelist.net/images/characters/13/109120.jpg", "Hiroshi Mitarai": "https://cdn.myanimelist.net/images/characters/7/109115.jpg", "Louise Fran\u00e7oise Le Blanc de La Valli\u00e8re": "https://cdn.myanimelist.net/images/characters/8/70553.jpg", "Saito Hiraga": "https://cdn.myanimelist.net/images/characters/13/50370.jpg", "Mitsuki Kouyama": "https://cdn.myanimelist.net/images/characters/9/34521.jpg", "Allen Walker": "https://cdn.myanimelist.net/images/characters/9/72171.jpg", "Yuu Kanda": "https://cdn.myanimelist.net/images/characters/9/68714.jpg", "Lenalee Lee": "https://cdn.myanimelist.net/images/characters/12/40740.jpg", "Komui Lee": "https://cdn.myanimelist.net/images/characters/14/74738.jpg", "Daisuke Niwa": "https://cdn.myanimelist.net/images/characters/16/81279.jpg", "Dark Mousy": "https://cdn.myanimelist.net/images/characters/9/125869.jpg", "Sakura Haruno": "https://cdn.myanimelist.net/images/characters/9/69275.jpg", "Negi Springfield": "https://cdn.myanimelist.net/images/characters/4/302932.jpg", "Kenshin Himura": "https://cdn.myanimelist.net/images/characters/8/73810.jpg", "Kaoru Kamiya": "https://cdn.myanimelist.net/images/characters/12/317795.jpg", "Sanosuke Sagara": "https://cdn.myanimelist.net/images/characters/3/256293.jpg", "Yahiko Myoujin": "https://cdn.myanimelist.net/images/characters/12/256281.jpg", "Megumi Takani": "https://cdn.myanimelist.net/images/characters/14/256301.jpg", "Kirara ": "https://cdn.myanimelist.net/images/characters/10/80677.jpg", "Kambei Shimada": "https://cdn.myanimelist.net/images/characters/11/49534.jpg", "Katsushiro Okamoto": "https://cdn.myanimelist.net/images/characters/11/80698.jpg", "Gorobei Katayama": "https://cdn.myanimelist.net/images/characters/12/49533.jpg", "Shichiroji ": "https://cdn.myanimelist.net/images/characters/10/80681.jpg", "Kikuchiyo ": "https://cdn.myanimelist.net/images/characters/14/47141.jpg", "Heihachi Hayashida": "https://cdn.myanimelist.net/images/characters/3/68801.jpg", "Kyuzo ": "https://cdn.myanimelist.net/images/characters/9/80680.jpg", "Tetsunosuke Ichimura": "https://cdn.myanimelist.net/images/characters/6/72574.jpg", "Souji Okita": "https://cdn.myanimelist.net/images/characters/6/72567.jpg", "Vash the Stampede ": "https://cdn.myanimelist.net/images/characters/10/89607.jpg", "Toshizou Hijikata": "https://cdn.myanimelist.net/images/characters/14/72571.jpg", "Sanosuke Harada": "https://cdn.myanimelist.net/images/characters/6/40102.jpg", "Shinpachi Nagakura": "https://cdn.myanimelist.net/images/characters/6/107950.jpg", "Susumu Yamazaki": "https://cdn.myanimelist.net/images/characters/8/72575.jpg", "You Asakura": "https://cdn.myanimelist.net/images/characters/4/60123.jpg", "Sousuke Sagara": "https://cdn.myanimelist.net/images/characters/9/139801.jpg", "Amidamaru ": "https://cdn.myanimelist.net/images/characters/3/60102.jpg", "Anna Kyouyama": "https://cdn.myanimelist.net/images/characters/8/86806.jpg", "Ren Tao": "https://cdn.myanimelist.net/images/characters/9/434149.jpg", "Hao Asakura": "https://cdn.myanimelist.net/images/characters/14/251443.jpg", "Horokeu Usui": "https://cdn.myanimelist.net/images/characters/13/81877.jpg", "Manta Oyamada": "https://cdn.myanimelist.net/images/characters/10/110871.jpg", "Tazusa Sakurano": "https://cdn.myanimelist.net/images/characters/12/82311.jpg", "Pete Pumps": "https://cdn.myanimelist.net/images/characters/10/61728.jpg", "Ayumu Narumi": "https://cdn.myanimelist.net/images/characters/14/55682.jpg", "Hiyono Yuizaki": "https://cdn.myanimelist.net/images/characters/13/98615.jpg", " Sakaki": "https://cdn.myanimelist.net/images/characters/14/56155.jpg", "Tomo Takino": "https://cdn.myanimelist.net/images/characters/9/48176.jpg", "Koyomi Mizuhara": "https://cdn.myanimelist.net/images/characters/2/56154.jpg", "Ayumu Kasuga": "https://cdn.myanimelist.net/images/characters/3/27890.jpg", "Kantarou Ichinomiya": "https://cdn.myanimelist.net/images/characters/12/55504.jpg", "Haruka ": "https://cdn.myanimelist.net/images/characters/7/55512.jpg", "Yukito Kunisaki": "https://cdn.myanimelist.net/images/characters/12/437329.jpg", "Misuzu Kamio": "https://cdn.myanimelist.net/images/characters/12/121658.jpg", "Rekka Hanabishi": "https://cdn.myanimelist.net/images/characters/16/85075.jpg", "Fuuko Kirisawa": "https://cdn.myanimelist.net/images/characters/2/85077.jpg", "Domon Ishijima": "https://cdn.myanimelist.net/images/characters/14/194663.jpg", "Tokiya Mikagami": "https://cdn.myanimelist.net/images/characters/6/85076.jpg", "Kaoru Koganei": "https://cdn.myanimelist.net/images/characters/3/93055.jpg", "Shima Katase": "https://cdn.myanimelist.net/images/characters/14/100418.jpg", "Kouta Otoyama": "https://cdn.myanimelist.net/images/characters/12/100417.jpg", "Arisa Glennorth": "https://cdn.myanimelist.net/images/characters/13/92407.jpg", "Azusa Hinomori": "https://cdn.myanimelist.net/images/characters/1/197.jpg", "Tenma Tsukamoto": "https://cdn.myanimelist.net/images/characters/11/30856.jpg", "Kenji Harima": "https://cdn.myanimelist.net/images/characters/10/29703.jpg", "Ouji Karasuma": "https://cdn.myanimelist.net/images/characters/12/128915.jpg", "Eri Sawachika": "https://cdn.myanimelist.net/images/characters/11/69392.jpg", "Yakumo Tsukamoto": "https://cdn.myanimelist.net/images/characters/16/69481.jpg", "Mikoto Suou": "https://cdn.myanimelist.net/images/characters/14/66180.jpg", "Akira Takano": "https://cdn.myanimelist.net/images/characters/3/34130.jpg", "Haruki Hanai": "https://cdn.myanimelist.net/images/characters/4/73660.jpg", "Shigure Souma": "https://cdn.myanimelist.net/images/characters/5/402891.jpg", "Tooru Honda": "https://cdn.myanimelist.net/images/characters/2/384113.jpg", "Yuki Souma": "https://cdn.myanimelist.net/images/characters/8/384112.jpg", "Kyou Souma": "https://cdn.myanimelist.net/images/characters/11/413334.jpg", "Kisuke Urahara": "https://cdn.myanimelist.net/images/characters/15/149491.jpg", "Ran Fujimiya": "https://cdn.myanimelist.net/images/characters/11/54553.jpg", "Omi Tsukiyono": "https://cdn.myanimelist.net/images/characters/12/54588.jpg", "Ken Hidaka": "https://cdn.myanimelist.net/images/characters/13/54589.jpg", "Youji Kudou": "https://cdn.myanimelist.net/images/characters/14/54554.jpg", "Sena Izumi": "https://cdn.myanimelist.net/images/characters/8/456634.jpg", "Kyou Aguri": "https://cdn.myanimelist.net/images/characters/14/456633.jpg", "Sanzou Genjou": "https://cdn.myanimelist.net/images/characters/2/66949.jpg", "Gokuu Son": "https://cdn.myanimelist.net/images/characters/15/72546.jpg", "Hakkai Cho": "https://cdn.myanimelist.net/images/characters/12/66948.jpg", "Gojou Sha": "https://cdn.myanimelist.net/images/characters/7/66950.jpg", "Risa Harada": "https://cdn.myanimelist.net/images/characters/6/41251.jpg", "Riku Harada": "https://cdn.myanimelist.net/images/characters/16/125863.jpg", "Satoshi Hiwatari": "https://cdn.myanimelist.net/images/characters/11/125825.jpg", "Krad ": "https://cdn.myanimelist.net/images/characters/14/54643.jpg", "Hideki Motosuwa": "https://cdn.myanimelist.net/images/characters/4/44770.jpg", "Hiromu Shinbo": "https://cdn.myanimelist.net/images/characters/9/139371.jpg", "Chii ": "https://cdn.myanimelist.net/images/characters/6/92991.jpg", "Chitose Hibiya": "https://cdn.myanimelist.net/images/characters/4/144173.jpg", "Minoru Kokubunji": "https://cdn.myanimelist.net/images/characters/2/139267.jpg", "Kotoko ": "https://cdn.myanimelist.net/images/characters/9/146069.jpg", "Sumomo ": "https://cdn.myanimelist.net/images/characters/11/55459.jpg", "Yoshiyuki Kojima": "https://cdn.myanimelist.net/images/characters/8/103262.jpg", "Hiroyasu Ueda": "https://cdn.myanimelist.net/images/characters/6/139271.jpg", "Yumi Omura": "https://cdn.myanimelist.net/images/characters/6/144215.jpg", "Kimihiro Watanuki": "https://cdn.myanimelist.net/images/characters/14/47223.jpg", "Yuuko Ichihara": "https://cdn.myanimelist.net/images/characters/10/93193.jpg", "Takaya Ougi": "https://cdn.myanimelist.net/images/characters/5/77055.jpg", "Nobutsuna Naoe": "https://cdn.myanimelist.net/images/characters/6/77057.jpg", "Shuuhei Chiaki": "https://cdn.myanimelist.net/images/characters/6/77054.jpg", "Haruie Kakizaki": "https://cdn.myanimelist.net/images/characters/11/77056.jpg", "Kiba ": "https://cdn.myanimelist.net/images/characters/7/74309.jpg", "Tsume ": "https://cdn.myanimelist.net/images/characters/6/74310.jpg", "Hige ": "https://cdn.myanimelist.net/images/characters/10/53955.jpg", "Toboe ": "https://cdn.myanimelist.net/images/characters/16/84625.jpg", "Toushirou Hitsugaya": "https://cdn.myanimelist.net/images/characters/11/36579.jpg", "Chiyo Mihama": "https://cdn.myanimelist.net/images/characters/13/35084.jpg", "Nayuki Minase": "https://cdn.myanimelist.net/images/characters/12/75628.jpg", "Yuki Nagato": "https://cdn.myanimelist.net/images/characters/11/319309.jpg", "Ayu Tsukimiya": "https://cdn.myanimelist.net/images/characters/12/33327.jpg", "Haruhi Suzumiya": "https://cdn.myanimelist.net/images/characters/13/284136.jpg", "Kyon ": "https://cdn.myanimelist.net/images/characters/13/75369.jpg", "Mikuru Asahina": "https://cdn.myanimelist.net/images/characters/10/75526.jpg", "Itsuki Koizumi": "https://cdn.myanimelist.net/images/characters/14/75055.jpg", "Ryouko Asakura": "https://cdn.myanimelist.net/images/characters/15/79610.jpg", " Tsuruya": "https://cdn.myanimelist.net/images/characters/4/31011.jpg", " Taniguchi": "https://cdn.myanimelist.net/images/characters/2/50131.jpg", " Kunikida": "https://cdn.myanimelist.net/images/characters/7/85466.jpg", "Satoshi Imamiya": "https://cdn.myanimelist.net/images/characters/15/110165.jpg", "Arumi Asahina": "https://cdn.myanimelist.net/images/characters/5/112430.jpg", "Masayoshi Asahina": "https://cdn.myanimelist.net/images/characters/2/112434.jpg", "Mune-mune ": "https://cdn.myanimelist.net/images/characters/8/112428.jpg", "Sayaka Imamiya": "https://cdn.myanimelist.net/images/characters/6/112435.jpg", "Eutus ": "https://cdn.myanimelist.net/images/characters/3/112429.jpg", "Aki ": "https://cdn.myanimelist.net/images/characters/14/112431.jpg", "Kouhei ": "https://cdn.myanimelist.net/images/characters/4/112432.jpg", "Satsuki Kusakabe": "https://cdn.myanimelist.net/images/characters/4/55560.jpg", "Mei Kusakabe": "https://cdn.myanimelist.net/images/characters/4/278460.jpg", "Totoro ": "https://cdn.myanimelist.net/images/characters/16/81225.jpg", "Kanta Oogaki": "https://cdn.myanimelist.net/images/characters/6/63836.jpg", "Nekobasu ": "https://cdn.myanimelist.net/images/characters/15/55346.jpg", "Kaname Chidori": "https://cdn.myanimelist.net/images/characters/10/59128.jpg", "Teletha Testarossa": "https://cdn.myanimelist.net/images/characters/2/85956.jpg", "Tenchi Masaki": "https://cdn.myanimelist.net/images/characters/5/276392.jpg", "Pacifica Casull": "https://cdn.myanimelist.net/images/characters/10/36693.jpg", "Shannon Casull": "https://cdn.myanimelist.net/images/characters/16/92402.jpg", "Raquel Casull": "https://cdn.myanimelist.net/images/characters/6/92403.jpg", "Christopher Armalite": "https://cdn.myanimelist.net/images/characters/10/37739.jpg", "Winia Chester": "https://cdn.myanimelist.net/images/characters/13/68912.jpg", "Leopold Scorpse": "https://cdn.myanimelist.net/images/characters/8/37742.jpg", "Ayu Tateishi": "https://cdn.myanimelist.net/images/characters/16/82161.jpg", "Nina Sakura": "https://cdn.myanimelist.net/images/characters/11/82016.jpg"}